geodemo_zw/__init__.py
geodemo_zw/common.py
geodemo_zw/geodemo_zw.py
geodemo_zw/utils.py
geodemo_zw-0.0.5.dist-info/LICENSE
geodemo_zw-0.0.5.dist-info/METADATA
geodemo_zw-0.0.5.dist-info/WHEEL
geodemo_zw-0.0.5.dist-info/dependency_links.txt
geodemo_zw-0.0.5.dist-info/top_level.txt
geodemo_zw-0.0.5.dist-info/RECORD
