Metadata-Version: 2.1
Name: geodemo-zw
Version: 0.0.5
Summary: A geodeom from remote desktop
Home-page: https://github.com/DataGeoranger/geodemo_zw
Author: Zhaowei Wang
Author-email: zhaowei.wang1987@gmail.com
License: MIT license
Keywords: geodemo_zw
Platform: UNKNOWN
Classifier: Development Status :: 2 - Pre-Alpha
Classifier: Intended Audience :: Developers
Classifier: License :: OSI Approved :: MIT License
Classifier: Natural Language :: English
Classifier: Programming Language :: Python :: 3
Classifier: Programming Language :: Python :: 3.5
Classifier: Programming Language :: Python :: 3.6
Classifier: Programming Language :: Python :: 3.7
Classifier: Programming Language :: Python :: 3.8
Requires-Python: >=3.5
Requires-Dist: earthengine-api
Requires-Dist: folium
Requires-Dist: ipyleaflet
Requires-Dist: pyshp
